{
  "url": {
    "Value": [
      "https://secure.realtimesis.com/acitech/scanner/?scan=8CA48519-8FA3-4D1F-B169-A80AB4C4C2C9",
      "https://secure.realtimesis.com/acitech/scanner/?scan=C68A3E93-984C-42B7-9CCD-5738C432932E"
    ]
  },
  "tokenserver": {
    "Value": ""
  },
  "customtoken": {
    "Value": ""
  },
  "multipleurlmode": {
    "Value": "tabs"
  },
  "newwindowmode": {
    "Value": "tab"
  },
  "startupdelay": {
    "Value": 0
  },
  "rotaterate": {
    "Value": false
  },
  "displaysysteminfo": {
    "Value": "admin"
  },
  "allowprint": {
    "Value": false
  },
  "hidegslidescontrols": {
    "Value": false
  },
  "local": {
    "Value": true
  },
  "scheduledreset": {
    "Value": false
  },
  "reset": {
    "Value": 0.2
  },
  "clearcookiesreset": {
    "Value": false
  },
  "screensaverreloadinterval": {
    "Value": null
  },
  "hidecursor": {
    "Value": false
  },
  "disablecontextmenu": {
    "Value": false
  },
  "disabledrag": {
    "Value": false
  },
  "disabletouchhighlight": {
    "Value": false
  },
  "disableselection": {
    "Value": false
  },
  "newwindow": {
    "Value": false
  },
  "allowdownload": {
    "Value": true
  },
  "disallowupload": {
    "Value": false
  },
  "disallowiframes": {
    "Value": false
  },
  "useragent": {
    "Value": ""
  },
  "authorization": {
    "Value": ""
  },
  "username": {
    "Value": "admin"
  },
  "password": {
    "Value": "kioskadmin"
  },
  "remoteschedule": {
    "Value": false
  },
  "remotescheduleurl": {
    "Value": ""
  },
  "schedulepollinterval": {
    "Value": false
  },
  "sleepmode": {
    "Value": "display"
  },
  "resetcache": {
    "Value": false
  },
  "shownav": {
    "Value": true
  },
  "showbattery": {
    "Value": false
  },
  "screensaverwarningtime": {
    "Value": 0
  },
  "screensaverwarningmessage": {
    "Value": "Screensaver starting in {countdown} seconds..."
  }
}